{
  "global": {
    "Color": {
      "gray": {
        "100": {
          "value": "#919191",
          "type": "color",
          "description": "$palette-primary-100 (A9)\n\nhex: : #919191\nL*: 60.17 (60)\n\n#FFFFFF-4.5:1: false\n#FFFFFF-3.0:1: true\n#000000-4.5:1: true\n#000000-3.0:1: true\n"
        },
        "200": {
          "value": "#848484",
          "type": "color",
          "description": "$palette-primary-200 (A10)\n\nhex: : #848484\nL*: 55.15 (55)\n\n#FFFFFF-4.5:1: false\n#FFFFFF-3.0:1: true\n#000000-4.5:1: true\n#000000-3.0:1: true\n"
        },
        "300": {
          "value": "#767676",
          "type": "color",
          "description": "$palette-primary-300 (A11)\n\nhex: : #767676\nL*: 49.64 (50)\n\n#FFFFFF-4.5:1: true\n#FFFFFF-3.0:1: true\n#000000-4.5:1: true\n#000000-3.0:1: true\n"
        },
        "400": {
          "value": "#6a6a6a",
          "type": "color",
          "description": "$palette-primary-400 (A12)\n\nhex: : #6A6A6A\nL*: 44.82 (45)\n\n#FFFFFF-4.5:1: true\n#FFFFFF-3.0:1: true\n#000000-4.5:1: false\n#000000-3.0:1: true\n"
        },
        "500": {
          "value": "#525252",
          "type": "color",
          "description": "$palette-primary-500 (A14)\n\nhex: : #525252\nL*: 34.88 (35)\n\n#FFFFFF-4.5:1: true\n#FFFFFF-3.0:1: true\n#000000-4.5:1: false\n#000000-3.0:1: false\n"
        },
        "600": {
          "value": "#3b3b3b",
          "type": "color",
          "description": "$palette-primary-600 (A16)\n\nhex: : #3B3B3B\nL*: 24.87 (25)\n\n#FFFFFF-4.5:1: true\n#FFFFFF-3.0:1: true\n#000000-4.5:1: false\n#000000-3.0:1: false\n"
        },
        "700": {
          "value": "#262626",
          "type": "color",
          "description": "$palette-primary-700 (A18)\n\nhex: : #262626\nL*: 15.16 (15)\n\n#FFFFFF-4.5:1: true\n#FFFFFF-3.0:1: true\n#000000-4.5:1: false\n#000000-3.0:1: false\n"
        },
        "800": {
          "value": "#1a1a1a",
          "type": "color",
          "description": "$palette-primary-800 (A19)\n\nhex: : #1A1A1A\nL*: 9.26 (10)\n\n#FFFFFF-4.5:1: true\n#FFFFFF-3.0:1: true\n#000000-4.5:1: false\n#000000-3.0:1: false\n"
        },
        "900": {
          "value": "#111111",
          "type": "color",
          "description": "$palette-primary-900 (A20)\n\nhex: : #111111\nL*: 5.06 (5)\n\n#FFFFFF-4.5:1: true\n#FFFFFF-3.0:1: true\n#000000-4.5:1: false\n#000000-3.0:1: false\n"
        },
        "015": {
          "value": "#f8f8f8",
          "type": "color",
          "description": "$palette-primary-015 (A1)\n\nhex: : #F8F8F8\nL*: 97.58 (97.5)\n\n#FFFFFF-4.5:1: false\n#FFFFFF-3.0:1: false\n#000000-4.5:1: true\n#000000-3.0:1: true\n"
        },
        "025": {
          "value": "#f1f1f1",
          "type": "color",
          "description": "$palette-primary-025 (A2)\n\nhex: : #F1F1F1\nL*: 95.15 (95)\n\n#FFFFFF-4.5:1: false\n#FFFFFF-3.0:1: false\n#000000-4.5:1: true\n#000000-3.0:1: true\n"
        },
        "050": {
          "value": "#e2e2e2",
          "type": "color",
          "description": "$palette-primary-050 (A3)\n\nhex: : #E2E2E2\nL*: 89.88 (90)\n\n#FFFFFF-4.5:1: false\n#FFFFFF-3.0:1: false\n#000000-4.5:1: true\n#000000-3.0:1: true\n"
        },
        "075": {
          "value": "#c6c6c6",
          "type": "color",
          "description": "$palette-primary-075 (A5)\n\nhex: : #C6C6C6\nL*: 79.88 (80)\n\n#FFFFFF-4.5:1: false\n#FFFFFF-3.0:1: false\n#000000-4.5:1: true\n#000000-3.0:1: true\n"
        },
        "085": {
          "value": "#ababab",
          "type": "color",
          "description": "$palette-primary-085 (A7)\n\nhex: : #ABABAB\nL*: 69.98 (70)\n\n#FFFFFF-4.5:1: false\n#FFFFFF-3.0:1: false\n#000000-4.5:1: true\n#000000-3.0:1: true\n"
        }
      },
      "yellow": {
        "100": {
          "value": "#ae8d0f",
          "type": "color",
          "description": "$palette-secondary-100 (B9)\n\nhex: : #AE8D0F\nL*: 59.97 (60)\n\n#FFFFFF-4.5:1: false\n#FFFFFF-3.0:1: true\n#000000-4.5:1: true\n#000000-3.0:1: true\n"
        },
        "200": {
          "value": "#9e8106",
          "type": "color",
          "description": "$palette-secondary-200 (B10)\n\nhex: : #9E8106\nL*: 55.06 (55)\n\n#FFFFFF-4.5:1: false\n#FFFFFF-3.0:1: true\n#000000-4.5:1: true\n#000000-3.0:1: true\n"
        },
        "300": {
          "value": "#8f7400",
          "type": "color",
          "description": "$palette-secondary-300 (B11)\n\nhex: : #8F7400\nL*: 49.9 (50)\n\n#FFFFFF-4.5:1: true\n#FFFFFF-3.0:1: true\n#000000-4.5:1: true\n#000000-3.0:1: true\n"
        },
        "400": {
          "value": "#806808",
          "type": "color",
          "description": "$palette-secondary-400 (B12)\n\nhex: : #806808\nL*: 44.95 (45)\n\n#FFFFFF-4.5:1: true\n#FFFFFF-3.0:1: true\n#000000-4.5:1: false\n#000000-3.0:1: true\n"
        },
        "500": {
          "value": "#645003",
          "type": "color",
          "description": "$palette-secondary-500 (B14)\n\nhex: : #645003\nL*: 34.91 (35)\n\n#FFFFFF-4.5:1: true\n#FFFFFF-3.0:1: true\n#000000-4.5:1: false\n#000000-3.0:1: false\n"
        },
        "600": {
          "value": "#493a01",
          "type": "color",
          "description": "$palette-secondary-600 (B16)\n\nhex: : #493A01\nL*: 25.09 (25)\n\n#FFFFFF-4.5:1: true\n#FFFFFF-3.0:1: true\n#000000-4.5:1: false\n#000000-3.0:1: false\n"
        },
        "700": {
          "value": "#2f2504",
          "type": "color",
          "description": "$palette-secondary-700 (B18)\n\nhex: : #2F2504\nL*: 15.15 (15)\n\n#FFFFFF-4.5:1: true\n#FFFFFF-3.0:1: true\n#000000-4.5:1: false\n#000000-3.0:1: false\n"
        },
        "800": {
          "value": "#241a00",
          "type": "color",
          "description": "$palette-secondary-800 (B19)\n\nhex: : #241A00\nL*: 9.91 (10)\n\n#FFFFFF-4.5:1: true\n#FFFFFF-3.0:1: true\n#000000-4.5:1: false\n#000000-3.0:1: false\n"
        },
        "900": {
          "value": "#161000",
          "type": "color",
          "description": "$palette-secondary-900 (B20)\n\nhex: : #161000\nL*: 4.89 (5)\n\n#FFFFFF-4.5:1: true\n#FFFFFF-3.0:1: true\n#000000-4.5:1: false\n#000000-3.0:1: false\n"
        },
        "015": {
          "value": "#fef8e6",
          "type": "color",
          "description": "$palette-secondary-015 (B1)\n\nhex: : #FEF8E6\nL*: 97.6 (97.5)\n\n#FFFFFF-4.5:1: false\n#FFFFFF-3.0:1: false\n#000000-4.5:1: true\n#000000-3.0:1: true\n"
        },
        "025": {
          "value": "#fcf0cb",
          "type": "color",
          "description": "$palette-secondary-025 (B2)\n\nhex: : #FCF0CB\nL*: 94.88 (95)\n\n#FFFFFF-4.5:1: false\n#FFFFFF-3.0:1: false\n#000000-4.5:1: true\n#000000-3.0:1: true\n"
        },
        "050": {
          "value": "#fde18a",
          "type": "color",
          "description": "$palette-secondary-050 (B3)\n\nhex: : #FDE18A\nL*: 90.12 (90)\n\n#FFFFFF-4.5:1: false\n#FFFFFF-3.0:1: false\n#000000-4.5:1: true\n#000000-3.0:1: true\n"
        },
        "075": {
          "value": "#facc15",
          "type": "color",
          "description": "$palette-secondary-075 (B4)\n\nhex: : #FACC15\nL*: 83.74 (85)\n\n#FFFFFF-4.5:1: false\n#FFFFFF-3.0:1: false\n#000000-4.5:1: true\n#000000-3.0:1: true\n"
        },
        "085": {
          "value": "#cda70c",
          "type": "color",
          "description": "$palette-secondary-085 (B7)\n\nhex: : #CDA70C\nL*: 69.93 (70)\n\n#FFFFFF-4.5:1: false\n#FFFFFF-3.0:1: false\n#000000-4.5:1: true\n#000000-3.0:1: true\n"
        }
      },
      "green": {
        "100": {
          "value": "#27a470",
          "type": "color",
          "description": "$palette-tertiary-100 (C9)\n\nhex: : #27A470\nL*: 60.02 (60)\n\n#FFFFFF-4.5:1: false\n#FFFFFF-3.0:1: true\n#000000-4.5:1: true\n#000000-3.0:1: true\n"
        },
        "200": {
          "value": "#259566",
          "type": "color",
          "description": "$palette-tertiary-200 (C10)\n\nhex: : #259566\nL*: 54.91 (55)\n\n#FFFFFF-4.5:1: false\n#FFFFFF-3.0:1: true\n#000000-4.5:1: true\n#000000-3.0:1: true\n"
        },
        "300": {
          "value": "#1f865c",
          "type": "color",
          "description": "$palette-tertiary-300 (C11)\n\nhex: : #1F865C\nL*: 49.63 (50)\n\n#FFFFFF-4.5:1: true\n#FFFFFF-3.0:1: true\n#000000-4.5:1: true\n#000000-3.0:1: true\n"
        },
        "400": {
          "value": "#1c7952",
          "type": "color",
          "description": "$palette-tertiary-400 (C12)\n\nhex: : #1C7952\nL*: 44.98 (45)\n\n#FFFFFF-4.5:1: true\n#FFFFFF-3.0:1: true\n#000000-4.5:1: false\n#000000-3.0:1: true\n"
        },
        "500": {
          "value": "#145e3f",
          "type": "color",
          "description": "$palette-tertiary-500 (C14)\n\nhex: : #145E3F\nL*: 35.03 (35)\n\n#FFFFFF-4.5:1: true\n#FFFFFF-3.0:1: true\n#000000-4.5:1: false\n#000000-3.0:1: false\n"
        },
        "600": {
          "value": "#0d442d",
          "type": "color",
          "description": "$palette-tertiary-600 (C16)\n\nhex: : #0D442D\nL*: 24.98 (25)\n\n#FFFFFF-4.5:1: true\n#FFFFFF-3.0:1: true\n#000000-4.5:1: false\n#000000-3.0:1: false\n"
        },
        "700": {
          "value": "#062c1c",
          "type": "color",
          "description": "$palette-tertiary-700 (C18)\n\nhex: : #062C1C\nL*: 15.08 (15)\n\n#FFFFFF-4.5:1: true\n#FFFFFF-3.0:1: true\n#000000-4.5:1: false\n#000000-3.0:1: false\n"
        },
        "800": {
          "value": "#022113",
          "type": "color",
          "description": "$palette-tertiary-800 (C19)\n\nhex: : #022113\nL*: 10.16 (10)\n\n#FFFFFF-4.5:1: true\n#FFFFFF-3.0:1: true\n#000000-4.5:1: false\n#000000-3.0:1: false\n"
        },
        "900": {
          "value": "#03140b",
          "type": "color",
          "description": "$palette-tertiary-900 (C20)\n\nhex: : #03140B\nL*: 4.91 (5)\n\n#FFFFFF-4.5:1: true\n#FFFFFF-3.0:1: true\n#000000-4.5:1: false\n#000000-3.0:1: false\n"
        },
        "015": {
          "value": "#f1faf5",
          "type": "color",
          "description": "$palette-tertiary-015 (C1)\n\nhex: : #F1FAF5\nL*: 97.5 (97.5)\n\n#FFFFFF-4.5:1: false\n#FFFFFF-3.0:1: false\n#000000-4.5:1: true\n#000000-3.0:1: true\n"
        },
        "025": {
          "value": "#e4f5eb",
          "type": "color",
          "description": "$palette-tertiary-025 (C2)\n\nhex: : #E4F5EB\nL*: 95.08 (95)\n\n#FFFFFF-4.5:1: false\n#FFFFFF-3.0:1: false\n#000000-4.5:1: true\n#000000-3.0:1: true\n"
        },
        "050": {
          "value": "#c8ead7",
          "type": "color",
          "description": "$palette-tertiary-050 (C3)\n\nhex: : #C8EAD7\nL*: 89.87 (90)\n\n#FFFFFF-4.5:1: false\n#FFFFFF-3.0:1: false\n#000000-4.5:1: true\n#000000-3.0:1: true\n"
        },
        "075": {
          "value": "#93d4b1",
          "type": "color",
          "description": "$palette-tertiary-075 (C5)\n\nhex: : #93D4B1\nL*: 79.88 (80)\n\n#FFFFFF-4.5:1: false\n#FFFFFF-3.0:1: false\n#000000-4.5:1: true\n#000000-3.0:1: true\n"
        },
        "085": {
          "value": "#2cb67d",
          "type": "color",
          "description": "$palette-tertiary-085 (C8)\n\nhex: : #2CB67D\nL*: 66.11 (65)\n\n#FFFFFF-4.5:1: false\n#FFFFFF-3.0:1: false\n#000000-4.5:1: true\n#000000-3.0:1: true\n"
        }
      },
      "orange": {
        "100": {
          "value": "#f57c13",
          "type": "color",
          "description": "$palette-attention-100 (G8)\n\nhex: : #F57C13\nL*: 64.87 (65)\n\n#FFFFFF-4.5:1: false\n#FFFFFF-3.0:1: false\n#000000-4.5:1: true\n#000000-3.0:1: true\n"
        },
        "200": {
          "value": "#ce670e",
          "type": "color",
          "description": "$palette-attention-200 (G10)\n\nhex: : #CE670E\nL*: 54.93 (55)\n\n#FFFFFF-4.5:1: false\n#FFFFFF-3.0:1: true\n#000000-4.5:1: true\n#000000-3.0:1: true\n"
        },
        "300": {
          "value": "#b95d0e",
          "type": "color",
          "description": "$palette-attention-300 (G11)\n\nhex: : #B95D0E\nL*: 49.71 (50)\n\n#FFFFFF-4.5:1: true\n#FFFFFF-3.0:1: true\n#000000-4.5:1: true\n#000000-3.0:1: true\n"
        },
        "400": {
          "value": "#a95307",
          "type": "color",
          "description": "$palette-attention-400 (G12)\n\nhex: : #A95307\nL*: 45.14 (45)\n\n#FFFFFF-4.5:1: true\n#FFFFFF-3.0:1: true\n#000000-4.5:1: false\n#000000-3.0:1: true\n"
        },
        "500": {
          "value": "#843f04",
          "type": "color",
          "description": "$palette-attention-500 (G14)\n\nhex: : #843F04\nL*: 34.94 (35)\n\n#FFFFFF-4.5:1: true\n#FFFFFF-3.0:1: true\n#000000-4.5:1: false\n#000000-3.0:1: false\n"
        },
        "600": {
          "value": "#612d02",
          "type": "color",
          "description": "$palette-attention-600 (G16)\n\nhex: : #612D02\nL*: 25.02 (25)\n\n#FFFFFF-4.5:1: true\n#FFFFFF-3.0:1: true\n#000000-4.5:1: false\n#000000-3.0:1: false\n"
        },
        "700": {
          "value": "#401c00",
          "type": "color",
          "description": "$palette-attention-700 (G18)\n\nhex: : #401C00\nL*: 15.07 (15)\n\n#FFFFFF-4.5:1: true\n#FFFFFF-3.0:1: true\n#000000-4.5:1: false\n#000000-3.0:1: false\n"
        },
        "800": {
          "value": "#301307",
          "type": "color",
          "description": "$palette-attention-800 (G19)\n\nhex: : #301307\nL*: 9.87 (10)\n\n#FFFFFF-4.5:1: true\n#FFFFFF-3.0:1: true\n#000000-4.5:1: false\n#000000-3.0:1: false\n"
        },
        "900": {
          "value": "#1f0c02",
          "type": "color",
          "description": "$palette-attention-900 (G20)\n\nhex: : #1F0C02\nL*: 5.05 (5)\n\n#FFFFFF-4.5:1: true\n#FFFFFF-3.0:1: true\n#000000-4.5:1: false\n#000000-3.0:1: false\n"
        },
        "015": {
          "value": "#fff6f0",
          "type": "color",
          "description": "$palette-attention-015 (G1)\n\nhex: : #FFF6F0\nL*: 97.42 (97.5)\n\n#FFFFFF-4.5:1: false\n#FFFFFF-3.0:1: false\n#000000-4.5:1: true\n#000000-3.0:1: true\n"
        },
        "025": {
          "value": "#ffede1",
          "type": "color",
          "description": "$palette-attention-025 (G2)\n\nhex: : #FFEDE1\nL*: 94.85 (95)\n\n#FFFFFF-4.5:1: false\n#FFFFFF-3.0:1: false\n#000000-4.5:1: true\n#000000-3.0:1: true\n"
        },
        "050": {
          "value": "#fedcc8",
          "type": "color",
          "description": "$palette-attention-050 (G3)\n\nhex: : #FEDCC8\nL*: 90.06 (90)\n\n#FFFFFF-4.5:1: false\n#FFFFFF-3.0:1: false\n#000000-4.5:1: true\n#000000-3.0:1: true\n"
        },
        "075": {
          "value": "#ffb68a",
          "type": "color",
          "description": "$palette-attention-075 (G5)\n\nhex: : #FFB68A\nL*: 79.93 (80)\n\n#FFFFFF-4.5:1: false\n#FFFFFF-3.0:1: false\n#000000-4.5:1: true\n#000000-3.0:1: true\n"
        },
        "085": {
          "value": "#f8914b",
          "type": "color",
          "description": "$palette-attention-085 (G7)\n\nhex: : #F8914B\nL*: 69.98 (70)\n\n#FFFFFF-4.5:1: false\n#FFFFFF-3.0:1: false\n#000000-4.5:1: true\n#000000-3.0:1: true\n"
        }
      },
      "blue": {
        "100": {
          "value": "#508efe",
          "type": "color",
          "description": "$palette-info-100 (H9)\n\nhex: : #508EFE\nL*: 60.07 (60)\n\n#FFFFFF-4.5:1: false\n#FFFFFF-3.0:1: true\n#000000-4.5:1: true\n#000000-3.0:1: true\n"
        },
        "200": {
          "value": "#3c7dff",
          "type": "color",
          "description": "$palette-info-200 (H10)\n\nhex: : #3C7DFF\nL*: 54.91 (55)\n\n#FFFFFF-4.5:1: false\n#FFFFFF-3.0:1: true\n#000000-4.5:1: true\n#000000-3.0:1: true\n"
        },
        "300": {
          "value": "#216dfa",
          "type": "color",
          "description": "$palette-info-300 (H11)\n\nhex: : #216DFA\nL*: 49.69 (50)\n\n#FFFFFF-4.5:1: true\n#FFFFFF-3.0:1: true\n#000000-4.5:1: true\n#000000-3.0:1: true\n"
        },
        "400": {
          "value": "#035ef9",
          "type": "color",
          "description": "$palette-info-400 (H12)\n\nhex: : #035EF9\nL*: 45.44 (45)\n\n#FFFFFF-4.5:1: true\n#FFFFFF-3.0:1: true\n#000000-4.5:1: false\n#000000-3.0:1: true\n"
        },
        "500": {
          "value": "#0c47c2",
          "type": "color",
          "description": "$palette-info-500 (H14)\n\nhex: : #0C47C2\nL*: 34.96 (35)\n\n#FFFFFF-4.5:1: true\n#FFFFFF-3.0:1: true\n#000000-4.5:1: false\n#000000-3.0:1: false\n"
        },
        "600": {
          "value": "#08338f",
          "type": "color",
          "description": "$palette-info-600 (H16)\n\nhex: : #08338F\nL*: 24.96 (25)\n\n#FFFFFF-4.5:1: true\n#FFFFFF-3.0:1: true\n#000000-4.5:1: false\n#000000-3.0:1: false\n"
        },
        "700": {
          "value": "#002063",
          "type": "color",
          "description": "$palette-info-700 (H18)\n\nhex: : #002063\nL*: 15.13 (15)\n\n#FFFFFF-4.5:1: true\n#FFFFFF-3.0:1: true\n#000000-4.5:1: false\n#000000-3.0:1: false\n"
        },
        "800": {
          "value": "#02174a",
          "type": "color",
          "description": "$palette-info-800 (H19)\n\nhex: : #02174A\nL*: 9.95 (10)\n\n#FFFFFF-4.5:1: true\n#FFFFFF-3.0:1: true\n#000000-4.5:1: false\n#000000-3.0:1: false\n"
        },
        "900": {
          "value": "#000d36",
          "type": "color",
          "description": "$palette-info-900 (H20)\n\nhex: : #000D36\nL*: 5 (5)\n\n#FFFFFF-4.5:1: true\n#FFFFFF-3.0:1: true\n#000000-4.5:1: false\n#000000-3.0:1: false\n"
        },
        "015": {
          "value": "#f3f8ff",
          "type": "color",
          "description": "$palette-info-015 (H1)\n\nhex: : #F3F8FF\nL*: 97.39 (97.5)\n\n#FFFFFF-4.5:1: false\n#FFFFFF-3.0:1: false\n#000000-4.5:1: true\n#000000-3.0:1: true\n"
        },
        "025": {
          "value": "#e8f2ff",
          "type": "color",
          "description": "$palette-info-025 (H2)\n\nhex: : #E8F2FF\nL*: 95.11 (95)\n\n#FFFFFF-4.5:1: false\n#FFFFFF-3.0:1: false\n#000000-4.5:1: true\n#000000-3.0:1: true\n"
        },
        "050": {
          "value": "#d3e4ff",
          "type": "color",
          "description": "$palette-info-050 (H3)\n\nhex: : #D3E4FF\nL*: 90.12 (90)\n\n#FFFFFF-4.5:1: false\n#FFFFFF-3.0:1: false\n#000000-4.5:1: true\n#000000-3.0:1: true\n"
        },
        "075": {
          "value": "#a7c8fe",
          "type": "color",
          "description": "$palette-info-075 (H5)\n\nhex: : #A7C8FE\nL*: 80 (80)\n\n#FFFFFF-4.5:1: false\n#FFFFFF-3.0:1: false\n#000000-4.5:1: true\n#000000-3.0:1: true\n"
        },
        "085": {
          "value": "#7cabfe",
          "type": "color",
          "description": "$palette-info-085 (H7)\n\nhex: : #7CABFE\nL*: 69.87 (70)\n\n#FFFFFF-4.5:1: false\n#FFFFFF-3.0:1: false\n#000000-4.5:1: true\n#000000-3.0:1: true\n"
        }
      },
      "red": {
        "100": {
          "value": "#d4766e",
          "type": "color",
          "description": "$palette-error-100 (I9)\n\nhex: : #D4766E\nL*: 59.96 (60)\n\n#FFFFFF-4.5:1: false\n#FFFFFF-3.0:1: true\n#000000-4.5:1: true\n#000000-3.0:1: true\n"
        },
        "200": {
          "value": "#cc655e",
          "type": "color",
          "description": "$palette-error-200 (I10)\n\nhex: : #CC655E\nL*: 55.03 (55)\n\n#FFFFFF-4.5:1: false\n#FFFFFF-3.0:1: true\n#000000-4.5:1: true\n#000000-3.0:1: true\n"
        },
        "300": {
          "value": "#c4514b",
          "type": "color",
          "description": "$palette-error-300 (I11)\n\nhex: : #C4514B\nL*: 49.66 (50)\n\n#FFFFFF-4.5:1: true\n#FFFFFF-3.0:1: true\n#000000-4.5:1: true\n#000000-3.0:1: true\n"
        },
        "400": {
          "value": "#b52c2c",
          "type": "color",
          "description": "$palette-error-400 (I13)\n\nhex: : #B52C2C\nL*: 40.91 (40)\n\n#FFFFFF-4.5:1: true\n#FFFFFF-3.0:1: true\n#000000-4.5:1: false\n#000000-3.0:1: true\n"
        },
        "700": {
          "value": "#4d0e0e",
          "type": "color",
          "description": "$palette-error-700 (I18)\n\nhex: : #4D0E0E\nL*: 15.08 (15)\n\n#FFFFFF-4.5:1: true\n#FFFFFF-3.0:1: true\n#000000-4.5:1: false\n#000000-3.0:1: false\n"
        },
        "800": {
          "value": "#3c0804",
          "type": "color",
          "description": "$palette-error-800 (I19)\n\nhex: : #3C0804\nL*: 10.13 (10)\n\n#FFFFFF-4.5:1: true\n#FFFFFF-3.0:1: true\n#000000-4.5:1: false\n#000000-3.0:1: false\n"
        },
        "015": {
          "value": "#fef6f5",
          "type": "color",
          "description": "$palette-error-015 (I1)\n\nhex: : #FEF6F5\nL*: 97.46 (97.5)\n\n#FFFFFF-4.5:1: false\n#FFFFFF-3.0:1: false\n#000000-4.5:1: true\n#000000-3.0:1: true\n"
        },
        "025": {
          "value": "#faeeed",
          "type": "color",
          "description": "$palette-error-025 (I2)\n\nhex: : #FAEEED\nL*: 94.99 (95)\n\n#FFFFFF-4.5:1: false\n#FFFFFF-3.0:1: false\n#000000-4.5:1: true\n#000000-3.0:1: true\n"
        },
        "050": {
          "value": "#f7dcd9",
          "type": "color",
          "description": "$palette-error-050 (I3)\n\nhex: : #F7DCD9\nL*: 89.85 (90)\n\n#FFFFFF-4.5:1: false\n#FFFFFF-3.0:1: false\n#000000-4.5:1: true\n#000000-3.0:1: true\n"
        },
        "075": {
          "value": "#edbab4",
          "type": "color",
          "description": "$palette-error-075 (I5)\n\nhex: : #EDBAB4\nL*: 79.85 (80)\n\n#FFFFFF-4.5:1: false\n#FFFFFF-3.0:1: false\n#000000-4.5:1: true\n#000000-3.0:1: true\n"
        },
        "085": {
          "value": "#e19891",
          "type": "color",
          "description": "$palette-error-085 (I7)\n\nhex: : #E19891\nL*: 69.83 (70)\n\n#FFFFFF-4.5:1: false\n#FFFFFF-3.0:1: false\n#000000-4.5:1: true\n#000000-3.0:1: true\n"
        }
      },
      "black": {
        "005": {
          "value": "#0000000d",
          "type": "color",
          "description": "black (5% opacity)"
        },
        "010": {
          "value": "#0000001a",
          "type": "color",
          "description": "black (10% opacity)"
        },
        "020": {
          "value": "#00000033",
          "type": "color",
          "description": "black (20% opacity)"
        },
        "030": {
          "value": "#0000004d",
          "type": "color",
          "description": "black (30% opacity)"
        },
        "040": {
          "value": "#00000066",
          "type": "color",
          "description": "black (40% opacity)"
        },
        "050": {
          "value": "#00000080",
          "type": "color",
          "description": "black (50% opacity)"
        },
        "060": {
          "value": "#00000099",
          "type": "color",
          "description": "black (60% opacity)"
        },
        "070": {
          "value": "#000000b3",
          "type": "color",
          "description": "black (70% opacity)"
        },
        "080": {
          "value": "#000000cc",
          "type": "color",
          "description": "black (80% opacity)"
        },
        "090": {
          "value": "#000000e6",
          "type": "color",
          "description": "black (90% opacity)"
        },
        "095": {
          "value": "#000000f2",
          "type": "color",
          "description": "black (95% opacity)"
        }
      },
      "white": {
        "005": {
          "value": "#ffffff0d",
          "type": "color",
          "description": "white (5% opacity)"
        },
        "010": {
          "value": "#ffffff1a",
          "type": "color",
          "description": "white (10% opacity)"
        },
        "020": {
          "value": "#ffffff33",
          "type": "color",
          "description": "white (20% opacity)"
        },
        "030": {
          "value": "#ffffff4d",
          "type": "color",
          "description": "white (30% opacity)"
        },
        "040": {
          "value": "#ffffff66",
          "type": "color",
          "description": "white (40% opacity)"
        },
        "050": {
          "value": "#ffffff80",
          "type": "color",
          "description": "white (50% opacity)"
        },
        "060": {
          "value": "#ffffff99",
          "type": "color",
          "description": "white (60% opacity)"
        },
        "070": {
          "value": "#ffffffb3",
          "type": "color",
          "description": "white (70% opacity)"
        },
        "080": {
          "value": "#ffffffcc",
          "type": "color",
          "description": "white (80% opacity)"
        },
        "090": {
          "value": "#ffffffe6",
          "type": "color",
          "description": "white (90% opacity)"
        },
        "095": {
          "value": "#fffffff2",
          "type": "color",
          "description": "white (95% opacity)"
        }
      }
    }
  },
  "dark": {
    "theme": {
      "background": {
        "primary": {
          "value": "{Color.gray.800}",
          "type": "color"
        }
      },
      "foreground": {
        "primary": {
          "value": "{Color.gray.015}",
          "type": "color"
        },
        "on-accent": {
          "value": "{Color.gray.800}",
          "type": "color"
        }
      },
      "accent": {
        "primary": {
          "dark": {
            "value": "{Color.yellow.100}",
            "type": "color"
          },
          "default": {
            "value": "{Color.yellow.075}",
            "type": "color"
          },
          "light": {
            "value": "{Color.yellow.050}",
            "type": "color"
          },
          "subtle": {
            "value": "{Color.yellow.025}",
            "type": "color"
          },
          "disabled": {
            "value": "{Color.gray.400}",
            "type": "color"
          }
        },
        "secondary": {
          "dark": {
            "value": "{Color.green.100}",
            "type": "color"
          },
          "default": {
            "value": "{Color.green.075}",
            "type": "color"
          },
          "light": {
            "value": "{Color.green.050}",
            "type": "color"
          },
          "sublte": {
            "value": "{Color.green.025}",
            "type": "color"
          },
          "disabled": {
            "value": "{Color.gray.400}",
            "type": "color"
          }
        }
      }
    },
    "dropshadow medium": {
      "value": [
        {
          "color": "#000000",
          "type": "dropShadow",
          "x": 4,
          "y": 4,
          "blur": 15,
          "spread": 0
        },
        {
          "color": "#000000",
          "type": "dropShadow",
          "x": -4,
          "y": -4,
          "blur": 15,
          "spread": 0
        }
      ],
      "type": "boxShadow"
    },
    "btn": {
      "value": [
        {
          "color": "#93d4b180",
          "type": "dropShadow",
          "x": -1,
          "y": -1,
          "blur": 10,
          "spread": 0
        },
        {
          "color": "#93d4b180",
          "type": "dropShadow",
          "x": 1,
          "y": 1,
          "blur": 10,
          "spread": 0
        }
      ],
      "type": "boxShadow"
    }
  },
  "light": {
    "theme": {
      "background": {
        "primary": {
          "value": "{Color.gray.015}",
          "type": "color"
        }
      },
      "foreground": {
        "primary": {
          "value": "{Color.gray.800}",
          "type": "color"
        },
        "on-accent": {
          "value": "{Color.gray.015}",
          "type": "color"
        }
      },
      "accent": {
        "primary": {
          "dark": {
            "value": "{Color.yellow.100}",
            "type": "color"
          },
          "default": {
            "value": "{Color.yellow.075}",
            "type": "color"
          },
          "light": {
            "value": "{Color.yellow.050}",
            "type": "color"
          },
          "subtle": {
            "value": "{Color.yellow.025}",
            "type": "color"
          },
          "disabled": {
            "value": "{Color.gray.200}",
            "type": "color"
          }
        },
        "secondary": {
          "dark": {
            "value": "{Color.green.800}",
            "type": "color"
          },
          "default": {
            "value": "{Color.green.700}",
            "type": "color"
          },
          "light": {
            "value": "{Color.green.500}",
            "type": "color"
          },
          "sublte": {
            "value": "{Color.green.900}",
            "type": "color"
          },
          "disabled": {
            "value": "{Color.gray.400}",
            "type": "color"
          }
        }
      }
    },
    "dropshadow medium": {
      "value": [
        {
          "color": "#e0e0e0",
          "type": "dropShadow",
          "x": "-4",
          "y": "-4",
          "blur": "15",
          "spread": "0"
        },
        {
          "color": "#e0e0e0",
          "type": "dropShadow",
          "x": "4",
          "y": "4",
          "blur": "15",
          "spread": "0"
        }
      ],
      "type": "boxShadow"
    },
    "btn": {
      "value": [
        {
          "color": "#062c1c80",
          "type": "dropShadow",
          "x": "1",
          "y": "1",
          "blur": "10",
          "spread": "0"
        },
        {
          "color": "#062c1c80",
          "type": "dropShadow",
          "x": "-1",
          "y": "-1",
          "blur": "10",
          "spread": "0"
        }
      ],
      "type": "boxShadow"
    }
  },
  "$themes": [],
  "$metadata": {
    "tokenSetOrder": [
      "global",
      "dark",
      "light"
    ]
  }
}